healthcheck/__init__.py
healthcheck/apps.py
healthcheck/checks.py
healthcheck/urls.py
healthcheck/views.py
easy_health_check-1.0.0.dist-info/METADATA
easy_health_check-1.0.0.dist-info/WHEEL
easy_health_check-1.0.0.dist-info/licenses/LICENSE
easy_health_check-1.0.0.dist-info/RECORD
