Metadata-Version: 2.1
Name: easy-health-check
Version: 1.0.0
Summary: A simple healthcheck server
Project-URL: homepage, https://github.com/ahmadly/healthcheck
Project-URL: repository, https://github.com/ahmadly/healthcheck
Author-email: "Ahmad H." <i@ahmadly.com>
License-File: LICENSE
Classifier: License :: OSI Approved :: MIT License
Classifier: Operating System :: OS Independent
Classifier: Programming Language :: Python :: 3
Requires-Python: >=3.7
